rosstat/__init__.py
rosstat/flc.py
rosstat/helpers.py
rosstat/report.py
rosstat/schema.py
rosstat/validators/__init__.py
rosstat/validators/base.py
rosstat/validators/attr/__init__.py
rosstat/validators/attr/attr.py
rosstat/validators/control/__init__.py
rosstat/validators/control/control.py
rosstat/validators/control/exceptions.py
rosstat/validators/control/inspectors/__init__.py
rosstat/validators/control/inspectors/formula.py
rosstat/validators/control/inspectors/period.py
rosstat/validators/control/parser/__init__.py
rosstat/validators/control/parser/elements.py
rosstat/validators/control/parser/lexer.py
rosstat/validators/control/parser/parser.py
rosstat/validators/control/parser/specific.py
rosstat/validators/control/parser/value.py
rosstat/validators/format/__init__.py
rosstat/validators/format/exceptions.py
rosstat/validators/format/format.py
rosstat/validators/format/inspectors/__init__.py
rosstat/validators/format/inspectors/spec.py
rosstat/validators/format/inspectors/value.py
rosstat/validators/title/__init__.py
rosstat/validators/title/title.py
rosstat_flc-1.3.1.dist-info/LICENSE
rosstat_flc-1.3.1.dist-info/METADATA
rosstat_flc-1.3.1.dist-info/WHEEL
rosstat_flc-1.3.1.dist-info/top_level.txt
rosstat_flc-1.3.1.dist-info/RECORD
