Metadata-Version: 2.1
Name: rosstat-flc
Version: 1.3.1
Summary: Tool for format-logistic control of reports sent to RosStat
Home-page: https://github.com/WoolenSweater/rosstat_flc
Author: Nikita Ryabinin
Author-email: ryabinin.ne@gmail.com
License: MIT
Keywords: control,flc,format-logistic,processing,russian-specific,report,rosstat
Classifier: Intended Audience :: Developers
Classifier: License :: OSI Approved :: MIT License
Classifier: Natural Language :: Russian
Classifier: Programming Language :: Python :: 3
Classifier: Programming Language :: Python :: 3 :: Only
Classifier: Programming Language :: Python :: 3.7
Classifier: Programming Language :: Python :: 3.8
Classifier: Programming Language :: Python :: 3.9
Classifier: Programming Language :: Python :: 3.10
Classifier: Programming Language :: Python :: 3.11
Classifier: Topic :: Scientific/Engineering :: Information Analysis
Requires-Python: >=3.7
License-File: LICENSE
Requires-Dist: lxml
Requires-Dist: ply
